{
  "gateway": {
    "mode": "local",
    "auth": {
      "mode": "token"
    },
    "controlUi": {
      "enabled": true,
      "allowInsecureAuth": true
    }
  },
  "plugins": {
    "enabled": true,
    "load": {
      "paths": ["/home/node/.openclaw/extensions/ario-gateway"]
    },
    "entries": {
      "ario-gateway": {
        "enabled": true,
        "config": {
          "gatewayUrl": "http://core:4000",
          "timeout": 30000
        }
      }
    }
  },
  "tools": {
    "profile": "full"
  }
}
